[
    {
        "address_name": "경북 경주시 황남동 307-1",
        "category_group_code": "FD6",
        "category_group_name": "음식점",
        "category_name": "음식점 > 술집 > 칵테일바",
        "distance": "",
        "id": "44342375",
        "phone": "010-4855-1571",
        "place_name": "BAR분",
        "place_url": "http://place.map.kakao.com/44342375",
        "road_address_name": "경북 경주시 포석로 1058-7",
        "x": "129.210313637623",
        "y": "35.8356606729948"
    },
    {
        "address_name": "서울 성북구 안암동5가 101-46",
        "category_group_code": "FD6",
        "category_group_name": "음식점",
        "category_name": "음식점 > 술집 > 칵테일바",
        "distance": "",
        "id": "17382390",
        "phone": "010-5672-2252",
        "place_name": "DaddyJ Hookah Bar",
        "place_url": "http://place.map.kakao.com/17382390",
        "road_address_name": "서울 성북구 고려대로24길 3-3",
        "x": "127.02968169866",
        "y": "37.5861235035469"
    },
    {
        "address_name": "서울 강남구 논현동 42-7",
        "category_group_code": "FD6",
        "category_group_name": "음식점",
        "category_name": "음식점 > 술집 > 칵테일바",
        "distance": "",
        "id": "728281290",
        "phone": "02-517-0901",
        "place_name": "인피니티8 BAR",
        "place_url": "http://place.map.kakao.com/728281290",
        "road_address_name": "서울 강남구 강남대로132길 59",
        "x": "127.0258343249",
        "y": "37.5135111385933"
    },
    {
        "address_name": "경기 양주시 옥정동 1071",
        "category_group_code": "FD6",
        "category_group_name": "음식점",
        "category_name": "음식점 > 술집 > 칵테일바",
        "distance": "",
        "id": "400044855",
        "phone": "",
        "place_name": "히히bar",
        "place_url": "http://place.map.kakao.com/400044855",
        "road_address_name": "경기 양주시 옥정동로5사길 12",
        "x": "127.095607360559",
        "y": "37.8157254342288"
    },
    {
        "address_name": "경기 하남시 망월동 1098",
        "category_group_code": "FD6",
        "category_group_name": "음식점",
        "category_name": "음식점 > 술집 > 칵테일바",
        "distance": "",
        "id": "1200932955",
        "phone": "010-3758-1325",
        "place_name": "포레스트hookah bar",
        "place_url": "http://place.map.kakao.com/1200932955",
        "road_address_name": "경기 하남시 미사강변중앙로 193",
        "x": "127.18953496703016",
        "y": "37.56358357951554"
    },
    {
        "address_name": "서울 관악구 신림동 1430-48",
        "category_group_code": "FD6",
        "category_group_name": "음식점",
        "category_name": "음식점 > 술집 > 칵테일바",
        "distance": "",
        "id": "302005112",
        "phone": "010-4069-3774",
        "place_name": "하이위스키BAR",
        "place_url": "http://place.map.kakao.com/302005112",
        "road_address_name": "서울 관악구 신림동길 8",
        "x": "126.927786217796",
        "y": "37.4875059790524"
    },
    {
        "address_name": "강원특별자치도 원주시 단구동 1666",
        "category_group_code": "FD6",
        "category_group_name": "음식점",
        "category_name": "음식점 > 술집 > 칵테일바",
        "distance": "",
        "id": "2007303394",
        "phone": "0507-1379-0632",
        "place_name": "한나bar",
        "place_url": "http://place.map.kakao.com/2007303394",
        "road_address_name": "강원특별자치도 원주시 단관길 59",
        "x": "127.955020996541",
        "y": "37.3223173440703"
    },
    {
        "address_name": "제주특별자치도 제주시 한림읍 협재리 1583",
        "category_group_code": "FD6",
        "category_group_name": "음식점",
        "category_name": "음식점 > 술집 > 칵테일바",
        "distance": "",
        "id": "1837029094",
        "phone": "070-7802-0410",
        "place_name": "오드(ODE Music Bar)",
        "place_url": "http://place.map.kakao.com/1837029094",
        "road_address_name": "제주특별자치도 제주시 한림읍 한림로 410",
        "x": "126.24589216438193",
        "y": "33.39824292517034"
    },
    {
        "address_name": "서울 강남구 논현동 240-7",
        "category_group_code": "FD6",
        "category_group_name": "음식점",
        "category_name": "음식점 > 술집 > 칵테일바",
        "distance": "",
        "id": "169793624",
        "phone": "070-8844-2400",
        "place_name": "Bar240",
        "place_url": "http://place.map.kakao.com/169793624",
        "road_address_name": "서울 강남구 학동로 332",
        "x": "127.039194093519",
        "y": "37.516336612964"
    },
    {
        "address_name": "대구 동구 신천동 337-11",
        "category_group_code": "FD6",
        "category_group_name": "음식점",
        "category_name": "음식점 > 술집 > 칵테일바",
        "distance": "",
        "id": "1642320184",
        "phone": "",
        "place_name": "M bar",
        "place_url": "http://place.map.kakao.com/1642320184",
        "road_address_name": "대구 동구 동부로28길 39",
        "x": "128.628450890018",
        "y": "35.8724862887173"
    },
    {
        "address_name": "경기 평택시 신장동 690-122",
        "category_group_code": "FD6",
        "category_group_name": "음식점",
        "category_name": "음식점 > 술집 > 칵테일바",
        "distance": "",
        "id": "798800104",
        "phone": "010-2176-4170",
        "place_name": "BAR417",
        "place_url": "http://place.map.kakao.com/798800104",
        "road_address_name": "경기 평택시 국제로 106",
        "x": "127.04985645764614",
        "y": "37.077477994527236"
    },
    {
        "address_name": "인천 중구 중앙동3가 1-4",
        "category_group_code": "FD6",
        "category_group_name": "음식점",
        "category_name": "음식점 > 술집 > 칵테일바",
        "distance": "",
        "id": "190404088",
        "phone": "0507-1353-6574",
        "place_name": "Bar032",
        "place_url": "http://place.map.kakao.com/190404088",
        "road_address_name": "인천 중구 신포로27번길 29",
        "x": "126.623662010695",
        "y": "37.472087320631"
    },
    {
        "address_name": "광주 동구 대의동 83-2",
        "category_group_code": "FD6",
        "category_group_name": "음식점",
        "category_name": "음식점 > 술집 > 칵테일바",
        "distance": "",
        "id": "64316431",
        "phone": "010-2752-1478",
        "place_name": "암전bar",
        "place_url": "http://place.map.kakao.com/64316431",
        "road_address_name": "광주 동구 중앙로196번길 31",
        "x": "126.918604145279",
        "y": "35.1488335676042"
    },
    {
        "address_name": "서울 마포구 서교동 327-20",
        "category_group_code": "FD6",
        "category_group_name": "음식점",
        "category_name": "음식점 > 술집 > 칵테일바",
        "distance": "",
        "id": "1786554508",
        "phone": "0507-1444-3452",
        "place_name": "시모네타 BAR SHIMONETA",
        "place_url": "http://place.map.kakao.com/1786554508",
        "road_address_name": "서울 마포구 와우산로29길 14-8",
        "x": "126.929204758131",
        "y": "37.555079336324"
    },
    {
        "address_name": "대구 달서구 호산동 361-8",
        "category_group_code": "FD6",
        "category_group_name": "음식점",
        "category_name": "음식점 > 술집 > 칵테일바",
        "distance": "",
        "id": "19567099",
        "phone": "053-593-7078",
        "place_name": "아띠BAR",
        "place_url": "http://place.map.kakao.com/19567099",
        "road_address_name": "대구 달서구 호산동로35북길 2",
        "x": "128.48558698527825",
        "y": "35.85086772591267"
    },
    {
        "address_name": "인천 중구 중앙동3가 1-4",
        "category_group_code": "FD6",
        "category_group_name": "음식점",
        "category_name": "음식점 > 술집 > 칵테일바",
        "distance": "",
        "id": "190404088",
        "phone": "0507-1353-6574",
        "place_name": "Bar032",
        "place_url": "http://place.map.kakao.com/190404088",
        "road_address_name": "인천 중구 신포로27번길 29",
        "x": "126.623662010695",
        "y": "37.472087320631"
    },
    {
        "address_name": "광주 동구 대의동 83-2",
        "category_group_code": "FD6",
        "category_group_name": "음식점",
        "category_name": "음식점 > 술집 > 칵테일바",
        "distance": "",
        "id": "64316431",
        "phone": "010-2752-1478",
        "place_name": "암전bar",
        "place_url": "http://place.map.kakao.com/64316431",
        "road_address_name": "광주 동구 중앙로196번길 31",
        "x": "126.918604145279",
        "y": "35.1488335676042"
    },
    {
        "address_name": "서울 마포구 서교동 327-20",
        "category_group_code": "FD6",
        "category_group_name": "음식점",
        "category_name": "음식점 > 술집 > 칵테일바",
        "distance": "",
        "id": "1786554508",
        "phone": "0507-1444-3452",
        "place_name": "시모네타 BAR SHIMONETA",
        "place_url": "http://place.map.kakao.com/1786554508",
        "road_address_name": "서울 마포구 와우산로29길 14-8",
        "x": "126.929204758131",
        "y": "37.555079336324"
    },
    {
        "address_name": "대구 달서구 호산동 361-8",
        "category_group_code": "FD6",
        "category_group_name": "음식점",
        "category_name": "음식점 > 술집 > 칵테일바",
        "distance": "",
        "id": "19567099",
        "phone": "053-593-7078",
        "place_name": "아띠BAR",
        "place_url": "http://place.map.kakao.com/19567099",
        "road_address_name": "대구 달서구 호산동로35북길 2",
        "x": "128.48558698527825",
        "y": "35.85086772591267"
    },
    {
        "address_name": "인천 중구 중앙동3가 1-4",
        "category_group_code": "FD6",
        "category_group_name": "음식점",
        "category_name": "음식점 > 술집 > 칵테일바",
        "distance": "",
        "id": "190404088",
        "phone": "0507-1353-6574",
        "place_name": "Bar032",
        "place_url": "http://place.map.kakao.com/190404088",
        "road_address_name": "인천 중구 신포로27번길 29",
        "x": "126.623662010695",
        "y": "37.472087320631"
    },
    {
        "address_name": "광주 동구 대의동 83-2",
        "category_group_code": "FD6",
        "category_group_name": "음식점",
        "category_name": "음식점 > 술집 > 칵테일바",
        "distance": "",
        "id": "64316431",
        "phone": "010-2752-1478",
        "place_name": "암전bar",
        "place_url": "http://place.map.kakao.com/64316431",
        "road_address_name": "광주 동구 중앙로196번길 31",
        "x": "126.918604145279",
        "y": "35.1488335676042"
    },
    {
        "address_name": "서울 마포구 서교동 327-20",
        "category_group_code": "FD6",
        "category_group_name": "음식점",
        "category_name": "음식점 > 술집 > 칵테일바",
        "distance": "",
        "id": "1786554508",
        "phone": "0507-1444-3452",
        "place_name": "시모네타 BAR SHIMONETA",
        "place_url": "http://place.map.kakao.com/1786554508",
        "road_address_name": "서울 마포구 와우산로29길 14-8",
        "x": "126.929204758131",
        "y": "37.555079336324"
    },
    {
        "address_name": "대구 달서구 호산동 361-8",
        "category_group_code": "FD6",
        "category_group_name": "음식점",
        "category_name": "음식점 > 술집 > 칵테일바",
        "distance": "",
        "id": "19567099",
        "phone": "053-593-7078",
        "place_name": "아띠BAR",
        "place_url": "http://place.map.kakao.com/19567099",
        "road_address_name": "대구 달서구 호산동로35북길 2",
        "x": "128.48558698527825",
        "y": "35.85086772591267"
    }
]